markdown_contents_generator/__init__.py
markdown_contents_generator/behaviours.py
markdown_contents_generator/contents_builder.py
markdown_contents_generator/contents_parser.py
markdown_contents_generator/utils.py
markdown_contents_generator/cli/__init__.py
markdown_contents_generator-0.1.5.data/scripts/md-contents-generator
markdown_contents_generator-0.1.5.dist-info/LICENSE
markdown_contents_generator-0.1.5.dist-info/METADATA
markdown_contents_generator-0.1.5.dist-info/WHEEL
markdown_contents_generator-0.1.5.dist-info/top_level.txt
markdown_contents_generator-0.1.5.dist-info/RECORD
