Metadata-Version: 2.1
Name: markdown-contents-generator
Version: 0.1.5
Summary: Generate table of contents for markdown files
Home-page: https://github.com/fadich/markdown-contents-generator
Author: Fadi A.
Author-email: royalfadich@gmail.com
License: UNKNOWN
Keywords: markdown-contents-generator,md-contents-generator,md,markdown,contents,contents-generator,generator,content
Platform: UNKNOWN
License-File: LICENSE
